flask_qiniu.py
setup.py
Flask_qiniu.egg-info/PKG-INFO
Flask_qiniu.egg-info/SOURCES.txt
Flask_qiniu.egg-info/dependency_links.txt
Flask_qiniu.egg-info/not-zip-safe
Flask_qiniu.egg-info/requires.txt
Flask_qiniu.egg-info/top_level.txt