Metadata-Version: 1.1
Name: Flask-qiniu
Version: 1.1.4
Summary: Flask Qiniu extension
Home-page: https://github.com/humiaozuzu/flask-qiniu
Author: Miao Hu
Author-email: maplevalley8@gmail.com
License: BSD
Platform: any
Classifier: Environment :: Web Environment
Classifier: Intended Audience :: Developers
Classifier: License :: OSI Approved :: BSD License
Classifier: Operating System :: OS Independent
Classifier: Programming Language :: Python
Classifier: Topic :: Internet :: WWW/HTTP :: Dynamic Content
Classifier: Topic :: Software Development :: Libraries :: Python Modules
